setup.cfg
setup.py
corrector/__init__.py
corrector/config.py
corrector/detect.py
corrector/util.py
corrector/data/same_pinyin.txt
corrector/data/same_stroke.txt
corrector/data/train_input.txt
corrector/data/xingjinzi.txt
corrector/data/kenlm/zhwiki_bigram.arpa
corrector/data/kenlm/zhwiki_bigram.klm
corrector/data/kenlm/zhwiki_trigram.arpa
corrector/data/kenlm/zhwiki_trigram.klm
corrector/zhtools/__init__.py
corrector/zhtools/langconv.py
corrector/zhtools/zh_wiki.py
error_correction.egg-info/PKG-INFO
error_correction.egg-info/SOURCES.txt
error_correction.egg-info/dependency_links.txt
error_correction.egg-info/requires.txt
error_correction.egg-info/top_level.txt