Metadata-Version: 1.1
Name: error-correction
Version: 1.0.3
Summary: Chinese Text Error Correction for Natural Language Processing and Understanding
Home-page: https://github.com/Samurais/corrector
Author: Hai Liang Wang
Author-email: hailiang.hl.wang@gmail.com
License: MIT
Keywords: corpus,machine-learning,NLU,NLP,Synonyms,Similarity
Platform: UNKNOWN
Classifier: Intended Audience :: Developers
Classifier: License :: OSI Approved :: Apache Software License
Classifier: Operating System :: OS Independent
Classifier: Natural Language :: Chinese (Simplified)
Classifier: Natural Language :: Chinese (Traditional)
Classifier: Programming Language :: Python
Classifier: Programming Language :: Python :: 2
Classifier: Programming Language :: Python :: 2.7
Classifier: Programming Language :: Python :: 3
Classifier: Programming Language :: Python :: 3.5
Classifier: Programming Language :: Python :: 3.6
Classifier: Topic :: Text Processing
Classifier: Topic :: Text Processing :: Indexing
Classifier: Topic :: Text Processing :: Linguistic
